mailtm/__init__.py
mailtm/__main__.py
mailtm/cli.py
mailtm/py.typed
mailtm/abc/__init__.py
mailtm/abc/generic.py
mailtm/abc/modals.py
mailtm/core/__init__.py
mailtm/core/errors.py
mailtm/core/methods.py
mailtm/impls/__init__.py
mailtm/impls/client.py
mailtm/impls/pullers.py
mailtm/impls/xclient.py
mailtm/server/__init__.py
mailtm/server/cache.py
mailtm/server/events.py
mailtm/server/impl.py
mailtm/server/srv.py
mailtm_sdk-0.1.3.dist-info/LICENSE.md
mailtm_sdk-0.1.3.dist-info/METADATA
mailtm_sdk-0.1.3.dist-info/WHEEL
mailtm_sdk-0.1.3.dist-info/entry_points.txt
mailtm_sdk-0.1.3.dist-info/top_level.txt
mailtm_sdk-0.1.3.dist-info/RECORD
