Metadata-Version: 2.1
Name: mailtm-sdk
Version: 0.1.3
Summary: Mail.tm Stack Development Kit, designed to enhance your experience with the renowned temporary email service, mail.tm
Home-page: https://halfstackpgr.github.io/Mail.tm/
Author: Parth Mishra
Author-email: halfstackpgr@gmail.com
Maintainer: Parth Mishra
Maintainer-email: halfstackpgr@gmail.com
Classifier: Environment :: Console
Classifier: Intended Audience :: Developers
Classifier: Operating System :: OS Independent
Classifier: Programming Language :: Python :: 3.12
Classifier: Topic :: Software Development :: Libraries
Classifier: Topic :: Software Development :: Libraries :: Python Modules
Classifier: Typing :: Typed
License-File: LICENSE.md
Requires-Dist: aiohttp
Requires-Dist: requests
Requires-Dist: msgspec
Requires-Dist: colorama
